ipa_gui/__init__.py
ipa_gui/configurations.py
ipa_gui/logwindow.py
ipa_gui/main.py
ipa_gui/mainwindow.py
ipa_gui/networking.py
ipa_utils/__init__.py
ipa_utils/listener.py
ipa_utils/mock_icepap.py
ipassign/__init__.py
ipassign/enums.py
ipassign/message.py
ipassign/payload.py
ipassign/utils.py
icepap_ipassign-2.3.0.dist-info/METADATA
icepap_ipassign-2.3.0.dist-info/WHEEL
icepap_ipassign-2.3.0.dist-info/entry_points.txt
icepap_ipassign-2.3.0.dist-info/top_level.txt
icepap_ipassign-2.3.0.dist-info/RECORD
