Metadata-Version: 2.1
Name: icepap-ipassign
Version: 2.3.0
Summary: A tool to configure IcePAP network settings
Home-page: https://github.com/cydanil/icepap-ipassign
Author: Cyril Danilevski
Author-email: cyril.danilevski@esrf.fr
License: UNKNOWN
Platform: UNKNOWN
Classifier: Development Status :: 6 - Mature
Classifier: Environment :: X11 Applications :: Qt
Classifier: Intended Audience :: Developers
Classifier: Intended Audience :: Science/Research
Classifier: License :: OSI Approved :: BSD License
Classifier: Operating System :: POSIX :: Linux
Classifier: Operating System :: Microsoft :: Windows
Classifier: Topic :: Scientific/Engineering
Requires-Python: >=3.7
Requires-Dist: PyQt5 (>=5.12.0)
Requires-Dist: netifaces (>=0.10.9)
